line4py/__init__.py
line4py/client.py
line4py/config.py
line4py/session.py
line4py/thrift.py
line4py/token.py
line4py/api/__init__.py
line4py/api/poll.py
line4py/api/talk.py
line4py/service/__init__.py
line4py/service/AuthService/AuthService.py
line4py/service/AuthService/__init__.py
line4py/service/AuthService/ttypes.py
line4py/service/BuddyService/BuddyService.py
line4py/service/BuddyService/__init__.py
line4py/service/BuddyService/ttypes.py
line4py/service/CallService/CallService.py
line4py/service/CallService/__init__.py
line4py/service/CallService/ttypes.py
line4py/service/ChannelService/ChannelService.py
line4py/service/ChannelService/__init__.py
line4py/service/ChannelService/ttypes.py
line4py/service/PrimaryAccountInitService/PrimaryAccountInitService.py
line4py/service/PrimaryAccountInitService/__init__.py
line4py/service/PrimaryAccountInitService/ttypes.py
line4py/service/SecondaryQrCodeLoginPermitNoticeService/SecondaryQrCodeLoginPermitNoticeService.py
line4py/service/SecondaryQrCodeLoginPermitNoticeService/__init__.py
line4py/service/SecondaryQrCodeLoginPermitNoticeService/ttypes.py
line4py/service/SecondaryQrCodeLoginPermitService/SecondaryQrCodeLoginPermitService.py
line4py/service/SecondaryQrCodeLoginPermitService/__init__.py
line4py/service/SecondaryQrCodeLoginPermitService/ttypes.py
line4py/service/SecondaryQrCodeLoginService/SecondaryQrCodeLoginService.py
line4py/service/SecondaryQrCodeLoginService/__init__.py
line4py/service/SecondaryQrCodeLoginService/ttypes.py
line4py/service/ShopService/ShopService.py
line4py/service/ShopService/__init__.py
line4py/service/ShopService/ttypes.py
line4py/service/TalkService/TalkService.py
line4py/service/TalkService/__init__.py
line4py/service/TalkService/ttypes.py
line4py-1.0.0.dist-info/LICENSE
line4py-1.0.0.dist-info/METADATA
line4py-1.0.0.dist-info/WHEEL
line4py-1.0.0.dist-info/top_level.txt
line4py-1.0.0.dist-info/RECORD
