Metadata-Version: 2.1
Name: line4py
Version: 1.0.0
Summary: LINE's library for Python
Home-page: https://github.com/7rs/line4py
Author: R4zL
Author-email: UNKNOWN
License: MIT
Platform: UNKNOWN
Requires-Dist: certifi (==2020.4.5.1)
Requires-Dist: flake8 (==3.8.2)
Requires-Dist: gevent (==20.5.2)
Requires-Dist: geventhttpclient (==1.4.2)
Requires-Dist: greenlet (==0.4.16)
Requires-Dist: loguru (==0.5.0)
Requires-Dist: mccabe (==0.6.1)
Requires-Dist: pycodestyle (==2.6.0)
Requires-Dist: pyflakes (==2.2.0)
Requires-Dist: python-axolotl-curve25519 (==0.4.1.post2)
Requires-Dist: python-dotenv (==0.13.0)
Requires-Dist: six (==1.15.0)
Requires-Dist: thrift (==0.13.0)
Requires-Dist: yapf (==0.30.0)
Requires-Dist: zope.event (==4.4)
Requires-Dist: zope.interface (==5.1.0)
